README.rst
setup.py
Rockefeller.egg-info/PKG-INFO
Rockefeller.egg-info/SOURCES.txt
Rockefeller.egg-info/dependency_links.txt
Rockefeller.egg-info/requires.txt
Rockefeller.egg-info/top_level.txt
rockefeller/__init__.py
rockefeller/currency.py
rockefeller/exceptions.py
rockefeller/exchange_rates.py
rockefeller/money.py
rockefeller/openers.py
rockefeller/services.py
rockefeller/utils.py
rockefeller/gae/__init__.py
rockefeller/gae/currency.py
rockefeller/gae/exchange_rates.py
rockefeller/gae/models.py