Metadata-Version: 1.1
Name: Rockefeller
Version: 1.2.3
Summary: Money, currencies and exchange rates library.
Home-page: http://ikame.github.com/Rockefeller/
Author: ikame
Author-email: anler86@gmail.com
License: MIT
Keywords: money currency exchange rates
Platform: UNKNOWN
Classifier: Environment :: Plugins
Classifier: Environment :: Console
Classifier: Environment :: Web Environment
Classifier: Intended Audience :: Developers
Classifier: Intended Audience :: Financial and Insurance Industry
Classifier: Operating System :: OS Independent
Classifier: Programming Language :: Python :: 2.7
Classifier: Programming Language :: Python :: 3.3
Classifier: Topic :: Software Development :: Libraries :: Python Modules
Classifier: Topic :: Office/Business :: Financial
